tabla_02_SOP/tabla_02_SOP.v
module tabla_02_SOP();

reg A, B, C;
wire notA, notB, notC, ter1, ter2, ter3, out;

not a(notA, A);
not b(notB, B);
not c(notC, C);

and I(ter1, notA, notB, C);
and J(ter2, A, B, notC);
and K(ter3, A, B, C);


or U1(out, ter1, ter2, ter3);

initial begin

$display("| A B C | Y |");
$display("|-------|---|");
$monitor("| %b %b %b | %b |", A, B, C, out);
A = 0; B = 0; C = 0;
#1 C = 1;
#1 B = 1; C = 0;
#1 C = 1;
#1 A = 1; B = 0; C = 0;
#1 C = 1;
#1 B = 1; C = 0;
#1 C = 1;


end
initial
    begin
      $dumpfile("tabla_02_SOP_tb.vcd");
      $dumpvars(0,tabla_02_SOP);
    end
endmodule

tabla_02_SOP/tabla_02_SOP_tb.vcd
$date
	Sat Aug 01 14:09:51 2020
$end
$version
	Icarus Verilog
$end
$timescale
	1ps
$end
$scope module tabla_02_SOP $end
$var wire 1 ! notA $end
$var wire 1 " notB $end
$var wire 1 # notC $end
$var wire 1 $ out $end
$var wire 1 % ter1 $end
$var wire 1 & ter2 $end
$var wire 1 ' ter3 $end
$var reg 1 ( A $end
$var reg 1 ) B $end
$var reg 1 * C $end
$upscope $end
$enddefinitions $end
#0
$dumpvars
0*
0)
0(
0'
0&
0%
0$
1#
1"
1!
$end
#1
1$
1%
0#
1*
#2
0$
0%
1#
0"
0*
1)
#3
0#
1*
#4
1#
1"
0!
0*
0)
1(
#5
0#
1*
#6
1$
1&
1#
0"
0*
1)
#7
0&
1'
0#
1*
