tabla_01_SOP/tabla_01_SOP.v
module tabla_01_SOP();

reg A, B, C;
wire notA, notB, notC, ter1, ter2, ter3, ter4, ter5, out;

not a(notA, A);
not b(notB, B);
not c(notC, C);

and I(ter1, notA, notB, notC);
and J(ter2, notA, B, notC);
and K(ter3, A, notB, notC);
and L(ter4, A, notB, C);
and M(ter5, A, B, C);

or U1(out, ter1, ter2, ter3, ter4, ter5);

initial begin

$display("| A B C | Y |");
$display("|-------|---|");
$monitor("| %b %b %b | %b |", A, B, C, out);
A = 0; B = 0; C = 0;
#1 C = 1;
#1 B = 1; C = 0;
#1 C = 1;
#1 A = 1; B = 0; C = 0;
#1 C = 1;
#1 B = 1; C = 0;
#1 C = 1;

end
initial
    begin
      $dumpfile("tabla_01_SOP_tb.vcd");
      $dumpvars(0,tabla_01_SOP);
    end
endmodule

tabla_01_SOP/tabla_01_SOP_tb.vcd
$date
	Sat Aug 01 14:07:06 2020
$end
$version
	Icarus Verilog
$end
$timescale
	1ps
$end
$scope module tabla_01_SOP $end
$var wire 1 ! notA $end
$var wire 1 " notB $end
$var wire 1 # notC $end
$var wire 1 $ out $end
$var wire 1 % ter1 $end
$var wire 1 & ter2 $end
$var wire 1 ' ter3 $end
$var wire 1 ( ter4 $end
$var wire 1 ) ter5 $end
$var reg 1 * A $end
$var reg 1 + B $end
$var reg 1 , C $end
$upscope $end
$enddefinitions $end
#0
$dumpvars
0,
0+
0*
0)
0(
0'
0&
1%
1$
1#
1"
1!
$end
#1
0$
0%
0#
1,
#2
1$
1&
1#
0"
0,
1+
#3
0$
0&
0#
1,
#4
1$
1'
1#
1"
0!
0,
0+
1*
#5
0'
1(
0#
1,
#6
0$
0(
1#
0"
0,
1+
#7
1$
1)
0#
1,
