tabla_02_POS/tabla_02_POS.v
module tabla_02_POS();

reg A, B, C;
wire notA, notB, notC, ter1, ter2, ter3, ter4, ter5, out;

not a(notA, A);
not b(notB, B);
not c(notC, C);

or I(ter1, A, B, C);
or J(ter2, A, notB, C);
or K(ter3, A, notB, notC);
or M(ter4, notA, B, C);
or L(ter5, notA, B, notC);

and U2(out, ter1, ter2, ter3, ter4, ter5);


initial begin

$display("| A B C | Y |");
$display("|-------|---|");
$monitor("| %b %b %b | %b |", A, B, C, out);
A = 0; B = 0; C = 0;
#1 C = 1;
#1 B = 1; C = 0;
#1 C = 1;
#1 A = 1; B = 0; C = 0;
#1 C = 1;
#1 B = 1; C = 0;
#1 C = 1;


end
initial
    begin
      $dumpfile("tabla_02_POS_tb.vcd");
      $dumpvars(0,tabla_02_POS);
    end

endmodule

tabla_02_POS/tabla_02_POS_tb.vcd
$date
	Sat Aug 01 14:10:34 2020
$end
$version
	Icarus Verilog
$end
$timescale
	1ps
$end
$scope module tabla_02_POS $end
$var wire 1 ! notA $end
$var wire 1 " notB $end
$var wire 1 # notC $end
$var wire 1 $ out $end
$var wire 1 % ter1 $end
$var wire 1 & ter2 $end
$var wire 1 ' ter3 $end
$var wire 1 ( ter4 $end
$var wire 1 ) ter5 $end
$var reg 1 * A $end
$var reg 1 + B $end
$var reg 1 , C $end
$upscope $end
$enddefinitions $end
#0
$dumpvars
0,
0+
0*
1)
1(
1'
1&
0%
0$
1#
1"
1!
$end
#1
1$
1%
0#
1,
#2
0$
0&
1#
0"
0,
1+
#3
0'
1&
0#
1,
#4
1#
1)
0(
1"
1'
0!
0,
0+
1*
#5
0)
1(
0#
1,
#6
1$
1#
1)
0"
0,
1+
#7
0#
1,
